wiz_scpi.py
fpga_ethernet_control-0.0.2.dist-info/METADATA
fpga_ethernet_control-0.0.2.dist-info/WHEEL
fpga_ethernet_control-0.0.2.dist-info/top_level.txt
fpga_ethernet_control-0.0.2.dist-info/RECORD
